CS 233/Lab3/mux.v
// output = A (when control == 0) or B (when control == 1)
module mux2(out, A, B, control);
    output out;
    input  A, B;
    input  control;
    wire   wA, wB, not_control;
         
    not n1(not_control, control);
    and a1(wA, A, not_control);
    and a2(wB, B, control);
    or  o1(out, wA, wB);
endmodule // mux2

// output = A (when control == 00) or B (when control == 01) or
//          C (when control == 10) or D (when control == 11)
module mux4(out, A, B, C, D, control);
    output      out;
    input       A, B, C, D;
    input [1:0] control;
    wire w1,w2;
   
    mux2 m1(w1,A,B,control[0]);
    mux2 m2(w2,C,D,control[0]);
    mux2 m3(out,w1,w2,control[1]);
    
endmodule // mux4

CS 233/Lab3/logicunit.v
// 00 - AND, 01 - OR, 10 - NOR, 11 - XOR
module logicunit(out, A, B, control);
    output      out;
    input       A, B;
    input [1:0] control;
    wire	w1,w2,w3,w4;
 /*  
    not n1(w1,control[0]);
    not n2(w2,control[1]);
    not n3(not_A,A);
    not n4(not_B,B);
      
    //test for and
    and a1(w3,A,B,w1,w2);


    //test for xor
    xor x1(w4,control[0],control[1]);
    xor x2(w5,A,B);
    and a2(w6,w4,w5);


    //test for nor
    and a3(w7,control[1],w1);
    and a4(w8,not_A,not_B);
    and a5(w9,w7,w8);

    //test for or
    or o1(w10,A,B);
    and a6(w11,control[0],w2);
    and a7(w12,w10,w11);

    or o2(out,w3,w6,w9,w12);
  */
  and a1(w1,A,B);
  or o1(w2,A,B);
  nor n1(w3,A,B);
  xor x1(w4,A,B);


  mux4 m1(out,w1,w2,w3,w4,control[1:0]);


        
    

endmodule // logicunit

CS 233/Lab3/logicunit_tb.v
module logicunit_test;
    // exhaustively test your logic unit by adapting mux4_tb.v
    
    
    reg A_in, B_in;
    reg [1:0] control;
                               // these are inputs to "circuit under test"
                                              // use "reg" not "wire" so can assign a value
    wire out_out;                         // wires for the outputs of "circuit under test"

    logicunit log1(out_out, A_in, B_in, control[1:0]);  // the circuit under test
    
    initial begin                             // initial = run at beginning of simulation
                                              // begin/end = associate block with initial
 
        $dumpfile("logicunit.vcd");                 
        $dumpvars(0,logicunit_test);                 
                                               
        // test all four input combinations
        // remember that 2 inputs means 2^2 = 4 combinations
        // 3 inputs would mean 2^3 = 8 combinations to test, and so on
        // this is very similar to the input columns of a truth table
        A_in = 0; B_in = 0; control = 2'b00;  # 10;             // set initial values and wait 10 time units
        A_in = 0; B_in = 0; control = 2'b01;  # 10;            // change inputs and then wait 10 time units
        A_in = 0; B_in = 0; control = 2'b10;  # 10;            // as above
        A_in = 0; B_in = 0; control = 2'b11;  # 10;
        A_in = 0; B_in = 1; control = 2'b00;  # 10;            // set initial values and wait 10 time units
        A_in = 0; B_in = 1; control = 2'b01;  # 10;           // change inputs and then wait 10 time units
        A_in = 0; B_in = 1; control = 2'b10;  # 10;          // as above
        A_in = 0; B_in = 1; control = 2'b11;  # 10;
        A_in = 1; B_in = 0; control = 2'b00;  # 10;
        A_in = 1; B_in = 0; control = 2'b01;  # 10;
        A_in = 1; B_in = 0; control = 2'b10;  # 10;
        A_in = 1; B_in = 0; control = 2'b11;  # 10;
        A_in = 1; B_in = 1; control = 2'b00;  # 10;
        A_in = 1; B_in = 1; control = 2'b01;  # 10;
        A_in = 1; B_in = 1; control = 2'b10;  # 10;
        A_in = 1; B_in = 1; control = 2'b11;  # 10;
        
        $finish;                              // end the simulation
    end                      
    
    initial
        $monitor("At time %2t, A_in = %d  B_in = %d  control_in =%d  out_out = %d ",
                 $time, A_in, B_in, control, out_out);
endmodule // logicunit_test

CS 233/Lab3/logicunit.vcd
$date
	Fri Sep 15 15:44:28 2017
$end
$version
	Icarus Verilog
$end
$timescale
	1s
$end
$scope module logicunit_test $end
$var wire 1 ! out_out $end
$var reg 1 " A_in $end
$var reg 1 # B_in $end
$var reg 2 $ control [1:0] $end
$scope module log1 $end
$var wire 1 % A $end
$var wire 1 & B $end
$var wire 2 ' control [1:0] $end
$var wire 1 ! out $end
$var wire 1 ( w1 $end
$var wire 1 ) w2 $end
$var wire 1 * w3 $end
$var wire 1 + w4 $end
$scope module m1 $end
$var wire 1 ( A $end
$var wire 1 ) B $end
$var wire 1 * C $end
$var wire 1 + D $end
$var wire 2 , control [1:0] $end
$var wire 1 ! out $end
$var wire 1 - w1 $end
$var wire 1 . w2 $end
$scope module m1 $end
$var wire 1 ( A $end
$var wire 1 ) B $end
$var wire 1 / control $end
$var wire 1 0 not_control $end
$var wire 1 - out $end
$var wire 1 1 wA $end
$var wire 1 2 wB $end
$upscope $end
$scope module m2 $end
$var wire 1 * A $end
$var wire 1 + B $end
$var wire 1 3 control $end
$var wire 1 4 not_control $end
$var wire 1 . out $end
$var wire 1 5 wA $end
$var wire 1 6 wB $end
$upscope $end
$scope module m3 $end
$var wire 1 - A $end
$var wire 1 . B $end
$var wire 1 7 control $end
$var wire 1 8 not_control $end
$var wire 1 ! out $end
$var wire 1 9 wA $end
$var wire 1 : wB $end
$upscope $end
$upscope $end
$upscope $end
$upscope $end
$enddefinitions $end
#0
$dumpvars
0:
09
18
07
06
15
14
03
02
01
10
0/
1.
0-
b0 ,
0+
1*
0)
0(
b0 '
0&
0%
b0 $
0#
0"
0!
$end
#10
0.
05
00
04
1/
13
b1 $
b1 '
b1 ,
#20
1!
1:
1.
15
10
14
08
0/
03
17
b10 $
b10 '
b10 ,
#30
0!
0:
0.
05
00
04
1/
13
b11 $
b11 '
b11 ,
#40
10
14
18
0/
03
07
1)
0*
1+
b0 $
b0 '
b0 ,
1#
1&
#50
1!
19
1-
1.
00
12
04
16
1/
13
b1 $
b1 '
b1 ,
#60
0!
0-
0.
09
10
02
14
06
08
0:
0/
03
17
b10 $
b10 '
b10 ,
#70
1!
1:
1-
1.
00
12
04
16
1/
13
b11 $
b11 '
b11 ,
#80
0-
0.
09
0!
10
02
14
06
18
0:
0/
03
07
b0 $
b0 '
b0 ,
0#
0&
1"
1%
#90
1!
19
1-
1.
00
12
04
16
1/
13
b1 $
b1 '
b1 ,
#100
0!
0-
0.
09
10
02
14
06
08
0:
0/
03
17
b10 $
b10 '
b10 ,
#110
1!
1:
1-
1.
00
12
04
16
1/
13
b11 $
b11 '
b11 ,
#120
11
1-
19
1!
0.
10
02
14
18
0:
06
0/
03
07
1(
0+
b0 $
b0 '
b0 ,
1#
1&
#130
01
00
12
04
1/
13
b1 $
b1 '
b1 ,
#140
0!
11
1-
09
10
02
14
08
0/
03
17
b10 $
b10 '
b10 ,
#150
01
00
12
04
1/
13
b11 $
b11 '
b11 ,
